papi_sdk/__init__.py
papi_sdk/auth.py
papi_sdk/client.py
papi_sdk/converters.py
papi_sdk/models.py
papi_sdk/py.typed
papi_sdk/urllib3_compatibility.py
papi_sdk/vrm_bulk_client.py
papi_sdk/generated/setup.py
papi_sdk/generated/generated/__init__.py
papi_sdk/generated/generated/api_client.py
papi_sdk/generated/generated/api_response.py
papi_sdk/generated/generated/configuration.py
papi_sdk/generated/generated/exceptions.py
papi_sdk/generated/generated/py.typed
papi_sdk/generated/generated/rest.py
papi_sdk/generated/generated/api/__init__.py
papi_sdk/generated/generated/api/auth_api.py
papi_sdk/generated/generated/api/ccs_api.py
papi_sdk/generated/generated/api/citi_api.py
papi_sdk/generated/generated/api/delivery_areas_api.py
papi_sdk/generated/generated/api/dowjones_api.py
papi_sdk/generated/generated/api/markups_api.py
papi_sdk/generated/generated/api/ocus_api.py
papi_sdk/generated/generated/api/sales_cockpit_api.py
papi_sdk/generated/generated/api/sccs_api.py
papi_sdk/generated/generated/api/shopify_api.py
papi_sdk/generated/generated/api/vrm_api.py
papi_sdk/generated/generated/api/vrm_bulk_api.py
papi_sdk/generated/generated/api/vrm_std_api.py
papi_sdk/generated/generated/models/__init__.py
papi_sdk/generated/generated/models/auth_v2_token_post200_response.py
papi_sdk/generated/generated/models/v1_citi_beneficiary_search_get200_response.py
papi_sdk/generated/generated/models/v1_citi_beneficiary_search_get200_response_data.py
papi_sdk/generated/generated/models/v1_citi_beneficiary_search_get200_response_data_payment.py
papi_sdk/generated/generated/models/v1_citi_beneficiary_search_get200_response_data_payment_additional_information.py
papi_sdk/generated/generated/models/v1_citi_beneficiary_search_get200_response_data_payment_creditor.py
papi_sdk/generated/generated/models/v1_delivery_areas_batch_post200_response.py
papi_sdk/generated/generated/models/v1_delivery_areas_batch_post200_response_data_inner.py
dh_papi_sdk-2.0.0.dist-info/METADATA
dh_papi_sdk-2.0.0.dist-info/WHEEL
dh_papi_sdk-2.0.0.dist-info/top_level.txt
dh_papi_sdk-2.0.0.dist-info/RECORD
