Metadata-Version: 2.4
Name: dh-papi-sdk
Version: 2.0.0
Summary: Python SDK for Delivery Hero's Platform API APIGee routers
Author-email: Delivery Hero Platform Team <dh_salesforce_platform_api@deliveryhero.com>
License: MIT
Project-URL: Repository, https://github.com/deliveryhero/dh-sf-pa-apigee
Keywords: salesforce,api,sdk,bulk,deliveryhero
Classifier: Development Status :: 5 - Production/Stable
Classifier: Intended Audience :: Developers
Classifier: License :: OSI Approved :: MIT License
Classifier: Programming Language :: Python :: 3
Classifier: Programming Language :: Python :: 3.8
Classifier: Programming Language :: Python :: 3.9
Classifier: Programming Language :: Python :: 3.10
Classifier: Programming Language :: Python :: 3.11
Classifier: Programming Language :: Python :: 3.12
Classifier: Operating System :: OS Independent
Requires-Python: >=3.8
Requires-Dist: requests<3.0.0,>=2.25.0
Requires-Dist: pydantic<3.0.0,>=2.0.0
Requires-Dist: typing-extensions>=4.7.1
Requires-Dist: urllib3<1.27.0,>=1.26.0
Requires-Dist: python-dateutil>=2.8.0
Requires-Dist: certifi>=2021.5.25
